{
  "openapi": "3.0.4",
  "info": {
    "title": "RetailStoreManagement",
    "version": "1.0"
  },
  "paths": {
    "/api/Auth/login": {
      "post": {
        "tags": [
          "Auth"
        ],
        "requestBody": {
          "content": {
            "application/json": {
              "schema": {
                "$ref": "#/components/schemas/LoginRequest"
              }
            },
            "text/json": {
              "schema": {
                "$ref": "#/components/schemas/LoginRequest"
              }
            },
            "application/*+json": {
              "schema": {
                "$ref": "#/components/schemas/LoginRequest"
              }
            }
          }
        },
        "responses": {
          "200": {
            "description": "OK"
          }
        }
      }
    },
    "/api/Auth/setup-admin": {
      "post": {
        "tags": [
          "Auth"
        ],
        "requestBody": {
          "content": {
            "application/json": {
              "schema": {
                "$ref": "#/components/schemas/CreateUserRequest"
              }
            },
            "text/json": {
              "schema": {
                "$ref": "#/components/schemas/CreateUserRequest"
              }
            },
            "application/*+json": {
              "schema": {
                "$ref": "#/components/schemas/CreateUserRequest"
              }
            }
          }
        },
        "responses": {
          "200": {
            "description": "OK"
          }
        }
      }
    },
    "/api/Auth/refresh": {
      "post": {
        "tags": [
          "Auth"
        ],
        "requestBody": {
          "content": {
            "application/json": {
              "schema": {
                "$ref": "#/components/schemas/RefreshTokenRequest"
              }
            },
            "text/json": {
              "schema": {
                "$ref": "#/components/schemas/RefreshTokenRequest"
              }
            },
            "application/*+json": {
              "schema": {
                "$ref": "#/components/schemas/RefreshTokenRequest"
              }
            }
          }
        },
        "responses": {
          "200": {
            "description": "OK"
          }
        }
      }
    },
    "/api/Auth/logout": {
      "post": {
        "tags": [
          "Auth"
        ],
        "requestBody": {
          "content": {
            "application/json": {
              "schema": {
                "$ref": "#/components/schemas/LogoutRequest"
              }
            },
            "text/json": {
              "schema": {
                "$ref": "#/components/schemas/LogoutRequest"
              }
            },
            "application/*+json": {
              "schema": {
                "$ref": "#/components/schemas/LogoutRequest"
              }
            }
          }
        },
        "responses": {
          "200": {
            "description": "OK"
          }
        }
      }
    },
    "/api/admin/categories": {
      "get": {
        "tags": [
          "Categories"
        ],
        "parameters": [
          {
            "name": "Page",
            "in": "query",
            "schema": {
              "type": "integer",
              "format": "int32"
            }
          },
          {
            "name": "PageSize",
            "in": "query",
            "schema": {
              "type": "integer",
              "format": "int32"
            }
          },
          {
            "name": "Search",
            "in": "query",
            "schema": {
              "type": "string"
            }
          },
          {
            "name": "SortBy",
            "in": "query",
            "schema": {
              "type": "string"
            }
          },
          {
            "name": "SortDesc",
            "in": "query",
            "schema": {
              "type": "boolean"
            }
          }
        ],
        "responses": {
          "200": {
            "description": "OK"
          }
        }
      },
      "post": {
        "tags": [
          "Categories"
        ],
        "requestBody": {
          "content": {
            "application/json": {
              "schema": {
                "$ref": "#/components/schemas/CreateCategoryRequest"
              }
            },
            "text/json": {
              "schema": {
                "$ref": "#/components/schemas/CreateCategoryRequest"
              }
            },
            "application/*+json": {
              "schema": {
                "$ref": "#/components/schemas/CreateCategoryRequest"
              }
            }
          }
        },
        "responses": {
          "200": {
            "description": "OK"
          }
        }
      }
    },
    "/api/admin/categories/{id}": {
      "get": {
        "tags": [
          "Categories"
        ],
        "parameters": [
          {
            "name": "id",
            "in": "path",
            "required": true,
            "schema": {
              "type": "integer",
              "format": "int32"
            }
          }
        ],
        "responses": {
          "200": {
            "description": "OK"
          }
        }
      },
      "put": {
        "tags": [
          "Categories"
        ],
        "parameters": [
          {
            "name": "id",
            "in": "path",
            "required": true,
            "schema": {
              "type": "integer",
              "format": "int32"
            }
          }
        ],
        "requestBody": {
          "content": {
            "application/json": {
              "schema": {
                "$ref": "#/components/schemas/UpdateCategoryRequest"
              }
            },
            "text/json": {
              "schema": {
                "$ref": "#/components/schemas/UpdateCategoryRequest"
              }
            },
            "application/*+json": {
              "schema": {
                "$ref": "#/components/schemas/UpdateCategoryRequest"
              }
            }
          }
        },
        "responses": {
          "200": {
            "description": "OK"
          }
        }
      },
      "delete": {
        "tags": [
          "Categories"
        ],
        "parameters": [
          {
            "name": "id",
            "in": "path",
            "required": true,
            "schema": {
              "type": "integer",
              "format": "int32"
            }
          }
        ],
        "responses": {
          "200": {
            "description": "OK"
          }
        }
      }
    },
    "/api/admin/customers": {
      "get": {
        "tags": [
          "Customers"
        ],
        "parameters": [
          {
            "name": "Page",
            "in": "query",
            "schema": {
              "type": "integer",
              "format": "int32"
            }
          },
          {
            "name": "PageSize",
            "in": "query",
            "schema": {
              "type": "integer",
              "format": "int32"
            }
          },
          {
            "name": "Search",
            "in": "query",
            "schema": {
              "type": "string"
            }
          },
          {
            "name": "SortBy",
            "in": "query",
            "schema": {
              "type": "string"
            }
          },
          {
            "name": "SortDesc",
            "in": "query",
            "schema": {
              "type": "boolean"
            }
          }
        ],
        "responses": {
          "200": {
            "description": "OK"
          }
        }
      },
      "post": {
        "tags": [
          "Customers"
        ],
        "requestBody": {
          "content": {
            "application/json": {
              "schema": {
                "$ref": "#/components/schemas/CreateCustomerRequest"
              }
            },
            "text/json": {
              "schema": {
                "$ref": "#/components/schemas/CreateCustomerRequest"
              }
            },
            "application/*+json": {
              "schema": {
                "$ref": "#/components/schemas/CreateCustomerRequest"
              }
            }
          }
        },
        "responses": {
          "200": {
            "description": "OK"
          }
        }
      }
    },
    "/api/admin/customers/{id}": {
      "get": {
        "tags": [
          "Customers"
        ],
        "parameters": [
          {
            "name": "id",
            "in": "path",
            "required": true,
            "schema": {
              "type": "integer",
              "format": "int32"
            }
          }
        ],
        "responses": {
          "200": {
            "description": "OK"
          }
        }
      },
      "put": {
        "tags": [
          "Customers"
        ],
        "parameters": [
          {
            "name": "id",
            "in": "path",
            "required": true,
            "schema": {
              "type": "integer",
              "format": "int32"
            }
          }
        ],
        "requestBody": {
          "content": {
            "application/json": {
              "schema": {
                "$ref": "#/components/schemas/UpdateCustomerRequest"
              }
            },
            "text/json": {
              "schema": {
                "$ref": "#/components/schemas/UpdateCustomerRequest"
              }
            },
            "application/*+json": {
              "schema": {
                "$ref": "#/components/schemas/UpdateCustomerRequest"
              }
            }
          }
        },
        "responses": {
          "200": {
            "description": "OK"
          }
        }
      },
      "delete": {
        "tags": [
          "Customers"
        ],
        "parameters": [
          {
            "name": "id",
            "in": "path",
            "required": true,
            "schema": {
              "type": "integer",
              "format": "int32"
            }
          }
        ],
        "responses": {
          "200": {
            "description": "OK"
          }
        }
      }
    },
    "/api/admin/inventory": {
      "get": {
        "tags": [
          "Inventory"
        ],
        "parameters": [
          {
            "name": "Page",
            "in": "query",
            "schema": {
              "type": "integer",
              "format": "int32"
            }
          },
          {
            "name": "PageSize",
            "in": "query",
            "schema": {
              "type": "integer",
              "format": "int32"
            }
          },
          {
            "name": "Search",
            "in": "query",
            "schema": {
              "type": "string"
            }
          },
          {
            "name": "SortBy",
            "in": "query",
            "schema": {
              "type": "string"
            }
          },
          {
            "name": "SortDesc",
            "in": "query",
            "schema": {
              "type": "boolean"
            }
          }
        ],
        "responses": {
          "200": {
            "description": "OK"
          }
        }
      }
    },
    "/api/admin/inventory/{productId}": {
      "get": {
        "tags": [
          "Inventory"
        ],
        "parameters": [
          {
            "name": "productId",
            "in": "path",
            "required": true,
            "schema": {
              "type": "integer",
              "format": "int32"
            }
          }
        ],
        "responses": {
          "200": {
            "description": "OK"
          }
        }
      },
      "patch": {
        "tags": [
          "Inventory"
        ],
        "parameters": [
          {
            "name": "productId",
            "in": "path",
            "required": true,
            "schema": {
              "type": "integer",
              "format": "int32"
            }
          }
        ],
        "requestBody": {
          "content": {
            "application/json": {
              "schema": {
                "$ref": "#/components/schemas/UpdateInventoryRequest"
              }
            },
            "text/json": {
              "schema": {
                "$ref": "#/components/schemas/UpdateInventoryRequest"
              }
            },
            "application/*+json": {
              "schema": {
                "$ref": "#/components/schemas/UpdateInventoryRequest"
              }
            }
          }
        },
        "responses": {
          "200": {
            "description": "OK"
          }
        }
      }
    },
    "/api/admin/inventory/low-stock": {
      "get": {
        "tags": [
          "Inventory"
        ],
        "responses": {
          "200": {
            "description": "OK"
          }
        }
      }
    },
    "/api/admin/inventory/{productId}/history": {
      "get": {
        "tags": [
          "Inventory"
        ],
        "parameters": [
          {
            "name": "productId",
            "in": "path",
            "required": true,
            "schema": {
              "type": "integer",
              "format": "int32"
            }
          },
          {
            "name": "Page",
            "in": "query",
            "schema": {
              "type": "integer",
              "format": "int32"
            }
          },
          {
            "name": "PageSize",
            "in": "query",
            "schema": {
              "type": "integer",
              "format": "int32"
            }
          },
          {
            "name": "Search",
            "in": "query",
            "schema": {
              "type": "string"
            }
          },
          {
            "name": "SortBy",
            "in": "query",
            "schema": {
              "type": "string"
            }
          },
          {
            "name": "SortDesc",
            "in": "query",
            "schema": {
              "type": "boolean"
            }
          }
        ],
        "responses": {
          "200": {
            "description": "OK"
          }
        }
      }
    },
    "/api/admin/orders": {
      "get": {
        "tags": [
          "Orders"
        ],
        "parameters": [
          {
            "name": "Status",
            "in": "query",
            "schema": {
              "type": "string"
            }
          },
          {
            "name": "CustomerId",
            "in": "query",
            "schema": {
              "type": "integer",
              "format": "int32"
            }
          },
          {
            "name": "UserId",
            "in": "query",
            "schema": {
              "type": "integer",
              "format": "int32"
            }
          },
          {
            "name": "StartDate",
            "in": "query",
            "schema": {
              "type": "string",
              "format": "date-time"
            }
          },
          {
            "name": "EndDate",
            "in": "query",
            "schema": {
              "type": "string",
              "format": "date-time"
            }
          },
          {
            "name": "Page",
            "in": "query",
            "schema": {
              "type": "integer",
              "format": "int32"
            }
          },
          {
            "name": "PageSize",
            "in": "query",
            "schema": {
              "type": "integer",
              "format": "int32"
            }
          },
          {
            "name": "Search",
            "in": "query",
            "schema": {
              "type": "string"
            }
          },
          {
            "name": "SortBy",
            "in": "query",
            "schema": {
              "type": "string"
            }
          },
          {
            "name": "SortDesc",
            "in": "query",
            "schema": {
              "type": "boolean"
            }
          }
        ],
        "responses": {
          "200": {
            "description": "OK"
          }
        }
      },
      "post": {
        "tags": [
          "Orders"
        ],
        "requestBody": {
          "content": {
            "application/json": {
              "schema": {
                "$ref": "#/components/schemas/CreateOrderRequest"
              }
            },
            "text/json": {
              "schema": {
                "$ref": "#/components/schemas/CreateOrderRequest"
              }
            },
            "application/*+json": {
              "schema": {
                "$ref": "#/components/schemas/CreateOrderRequest"
              }
            }
          }
        },
        "responses": {
          "200": {
            "description": "OK"
          }
        }
      }
    },
    "/api/admin/orders/{id}": {
      "get": {
        "tags": [
          "Orders"
        ],
        "parameters": [
          {
            "name": "id",
            "in": "path",
            "required": true,
            "schema": {
              "type": "integer",
              "format": "int32"
            }
          }
        ],
        "responses": {
          "200": {
            "description": "OK"
          }
        }
      }
    },
    "/api/admin/orders/{id}/status": {
      "patch": {
        "tags": [
          "Orders"
        ],
        "parameters": [
          {
            "name": "id",
            "in": "path",
            "required": true,
            "schema": {
              "type": "integer",
              "format": "int32"
            }
          }
        ],
        "requestBody": {
          "content": {
            "application/json": {
              "schema": {
                "$ref": "#/components/schemas/UpdateOrderStatusRequest"
              }
            },
            "text/json": {
              "schema": {
                "$ref": "#/components/schemas/UpdateOrderStatusRequest"
              }
            },
            "application/*+json": {
              "schema": {
                "$ref": "#/components/schemas/UpdateOrderStatusRequest"
              }
            }
          }
        },
        "responses": {
          "200": {
            "description": "OK"
          }
        }
      }
    },
    "/api/admin/orders/{orderId}/items": {
      "post": {
        "tags": [
          "Orders"
        ],
        "parameters": [
          {
            "name": "orderId",
            "in": "path",
            "required": true,
            "schema": {
              "type": "integer",
              "format": "int32"
            }
          }
        ],
        "requestBody": {
          "content": {
            "application/json": {
              "schema": {
                "$ref": "#/components/schemas/AddOrderItemRequest"
              }
            },
            "text/json": {
              "schema": {
                "$ref": "#/components/schemas/AddOrderItemRequest"
              }
            },
            "application/*+json": {
              "schema": {
                "$ref": "#/components/schemas/AddOrderItemRequest"
              }
            }
          }
        },
        "responses": {
          "200": {
            "description": "OK"
          }
        }
      }
    },
    "/api/admin/orders/{orderId}/items/{itemId}": {
      "put": {
        "tags": [
          "Orders"
        ],
        "parameters": [
          {
            "name": "orderId",
            "in": "path",
            "required": true,
            "schema": {
              "type": "integer",
              "format": "int32"
            }
          },
          {
            "name": "itemId",
            "in": "path",
            "required": true,
            "schema": {
              "type": "integer",
              "format": "int32"
            }
          }
        ],
        "requestBody": {
          "content": {
            "application/json": {
              "schema": {
                "$ref": "#/components/schemas/UpdateOrderItemRequest"
              }
            },
            "text/json": {
              "schema": {
                "$ref": "#/components/schemas/UpdateOrderItemRequest"
              }
            },
            "application/*+json": {
              "schema": {
                "$ref": "#/components/schemas/UpdateOrderItemRequest"
              }
            }
          }
        },
        "responses": {
          "200": {
            "description": "OK"
          }
        }
      },
      "delete": {
        "tags": [
          "Orders"
        ],
        "parameters": [
          {
            "name": "orderId",
            "in": "path",
            "required": true,
            "schema": {
              "type": "integer",
              "format": "int32"
            }
          },
          {
            "name": "itemId",
            "in": "path",
            "required": true,
            "schema": {
              "type": "integer",
              "format": "int32"
            }
          }
        ],
        "responses": {
          "200": {
            "description": "OK"
          }
        }
      }
    },
    "/api/admin/orders/{id}/invoice": {
      "get": {
        "tags": [
          "Orders"
        ],
        "parameters": [
          {
            "name": "id",
            "in": "path",
            "required": true,
            "schema": {
              "type": "integer",
              "format": "int32"
            }
          }
        ],
        "responses": {
          "200": {
            "description": "OK"
          }
        }
      }
    },
    "/api/admin/products": {
      "get": {
        "tags": [
          "Products"
        ],
        "parameters": [
          {
            "name": "CategoryId",
            "in": "query",
            "schema": {
              "type": "integer",
              "format": "int32"
            }
          },
          {
            "name": "SupplierId",
            "in": "query",
            "schema": {
              "type": "integer",
              "format": "int32"
            }
          },
          {
            "name": "MinPrice",
            "in": "query",
            "schema": {
              "type": "number",
              "format": "double"
            }
          },
          {
            "name": "MaxPrice",
            "in": "query",
            "schema": {
              "type": "number",
              "format": "double"
            }
          },
          {
            "name": "Page",
            "in": "query",
            "schema": {
              "type": "integer",
              "format": "int32"
            }
          },
          {
            "name": "PageSize",
            "in": "query",
            "schema": {
              "type": "integer",
              "format": "int32"
            }
          },
          {
            "name": "Search",
            "in": "query",
            "schema": {
              "type": "string"
            }
          },
          {
            "name": "SortBy",
            "in": "query",
            "schema": {
              "type": "string"
            }
          },
          {
            "name": "SortDesc",
            "in": "query",
            "schema": {
              "type": "boolean"
            }
          }
        ],
        "responses": {
          "200": {
            "description": "OK"
          }
        }
      },
      "post": {
        "tags": [
          "Products"
        ],
        "requestBody": {
          "content": {
            "application/json": {
              "schema": {
                "$ref": "#/components/schemas/CreateProductRequest"
              }
            },
            "text/json": {
              "schema": {
                "$ref": "#/components/schemas/CreateProductRequest"
              }
            },
            "application/*+json": {
              "schema": {
                "$ref": "#/components/schemas/CreateProductRequest"
              }
            }
          }
        },
        "responses": {
          "200": {
            "description": "OK"
          }
        }
      }
    },
    "/api/admin/products/{id}": {
      "get": {
        "tags": [
          "Products"
        ],
        "parameters": [
          {
            "name": "id",
            "in": "path",
            "required": true,
            "schema": {
              "type": "integer",
              "format": "int32"
            }
          }
        ],
        "responses": {
          "200": {
            "description": "OK"
          }
        }
      },
      "put": {
        "tags": [
          "Products"
        ],
        "parameters": [
          {
            "name": "id",
            "in": "path",
            "required": true,
            "schema": {
              "type": "integer",
              "format": "int32"
            }
          }
        ],
        "requestBody": {
          "content": {
            "application/json": {
              "schema": {
                "$ref": "#/components/schemas/UpdateProductRequest"
              }
            },
            "text/json": {
              "schema": {
                "$ref": "#/components/schemas/UpdateProductRequest"
              }
            },
            "application/*+json": {
              "schema": {
                "$ref": "#/components/schemas/UpdateProductRequest"
              }
            }
          }
        },
        "responses": {
          "200": {
            "description": "OK"
          }
        }
      },
      "delete": {
        "tags": [
          "Products"
        ],
        "parameters": [
          {
            "name": "id",
            "in": "path",
            "required": true,
            "schema": {
              "type": "integer",
              "format": "int32"
            }
          }
        ],
        "responses": {
          "200": {
            "description": "OK"
          }
        }
      }
    },
    "/api/admin/promotions": {
      "get": {
        "tags": [
          "Promotions"
        ],
        "parameters": [
          {
            "name": "Page",
            "in": "query",
            "schema": {
              "type": "integer",
              "format": "int32"
            }
          },
          {
            "name": "PageSize",
            "in": "query",
            "schema": {
              "type": "integer",
              "format": "int32"
            }
          },
          {
            "name": "Search",
            "in": "query",
            "schema": {
              "type": "string"
            }
          },
          {
            "name": "SortBy",
            "in": "query",
            "schema": {
              "type": "string"
            }
          },
          {
            "name": "SortDesc",
            "in": "query",
            "schema": {
              "type": "boolean"
            }
          }
        ],
        "responses": {
          "200": {
            "description": "OK"
          }
        }
      },
      "post": {
        "tags": [
          "Promotions"
        ],
        "requestBody": {
          "content": {
            "application/json": {
              "schema": {
                "$ref": "#/components/schemas/CreatePromotionRequest"
              }
            },
            "text/json": {
              "schema": {
                "$ref": "#/components/schemas/CreatePromotionRequest"
              }
            },
            "application/*+json": {
              "schema": {
                "$ref": "#/components/schemas/CreatePromotionRequest"
              }
            }
          }
        },
        "responses": {
          "200": {
            "description": "OK"
          }
        }
      }
    },
    "/api/admin/promotions/{id}": {
      "get": {
        "tags": [
          "Promotions"
        ],
        "parameters": [
          {
            "name": "id",
            "in": "path",
            "required": true,
            "schema": {
              "type": "integer",
              "format": "int32"
            }
          }
        ],
        "responses": {
          "200": {
            "description": "OK"
          }
        }
      },
      "put": {
        "tags": [
          "Promotions"
        ],
        "parameters": [
          {
            "name": "id",
            "in": "path",
            "required": true,
            "schema": {
              "type": "integer",
              "format": "int32"
            }
          }
        ],
        "requestBody": {
          "content": {
            "application/json": {
              "schema": {
                "$ref": "#/components/schemas/UpdatePromotionRequest"
              }
            },
            "text/json": {
              "schema": {
                "$ref": "#/components/schemas/UpdatePromotionRequest"
              }
            },
            "application/*+json": {
              "schema": {
                "$ref": "#/components/schemas/UpdatePromotionRequest"
              }
            }
          }
        },
        "responses": {
          "200": {
            "description": "OK"
          }
        }
      },
      "delete": {
        "tags": [
          "Promotions"
        ],
        "parameters": [
          {
            "name": "id",
            "in": "path",
            "required": true,
            "schema": {
              "type": "integer",
              "format": "int32"
            }
          }
        ],
        "responses": {
          "200": {
            "description": "OK"
          }
        }
      }
    },
    "/api/admin/promotions/validate": {
      "post": {
        "tags": [
          "Promotions"
        ],
        "requestBody": {
          "content": {
            "application/json": {
              "schema": {
                "$ref": "#/components/schemas/ValidatePromoRequest"
              }
            },
            "text/json": {
              "schema": {
                "$ref": "#/components/schemas/ValidatePromoRequest"
              }
            },
            "application/*+json": {
              "schema": {
                "$ref": "#/components/schemas/ValidatePromoRequest"
              }
            }
          }
        },
        "responses": {
          "200": {
            "description": "OK"
          }
        }
      }
    },
    "/api/admin/reports/revenue": {
      "get": {
        "tags": [
          "Reports"
        ],
        "parameters": [
          {
            "name": "StartDate",
            "in": "query",
            "required": true,
            "schema": {
              "type": "string",
              "format": "date-time"
            }
          },
          {
            "name": "EndDate",
            "in": "query",
            "required": true,
            "schema": {
              "type": "string",
              "format": "date-time"
            }
          },
          {
            "name": "GroupBy",
            "in": "query",
            "schema": {
              "pattern": "^(day|week|month)$",
              "type": "string"
            }
          }
        ],
        "responses": {
          "200": {
            "description": "OK"
          }
        }
      }
    },
    "/api/admin/reports/sales": {
      "get": {
        "tags": [
          "Reports"
        ],
        "parameters": [
          {
            "name": "StartDate",
            "in": "query",
            "required": true,
            "schema": {
              "type": "string",
              "format": "date-time"
            }
          },
          {
            "name": "EndDate",
            "in": "query",
            "required": true,
            "schema": {
              "type": "string",
              "format": "date-time"
            }
          },
          {
            "name": "GroupBy",
            "in": "query",
            "schema": {
              "pattern": "^(day|week|month)$",
              "type": "string"
            }
          },
          {
            "name": "CategoryId",
            "in": "query",
            "schema": {
              "type": "integer",
              "format": "int32"
            }
          }
        ],
        "responses": {
          "200": {
            "description": "OK"
          }
        }
      }
    },
    "/api/admin/reports/top-products": {
      "get": {
        "tags": [
          "Reports"
        ],
        "parameters": [
          {
            "name": "startDate",
            "in": "query",
            "schema": {
              "type": "string",
              "format": "date-time"
            }
          },
          {
            "name": "endDate",
            "in": "query",
            "schema": {
              "type": "string",
              "format": "date-time"
            }
          },
          {
            "name": "limit",
            "in": "query",
            "schema": {
              "type": "integer",
              "format": "int32",
              "default": 10
            }
          }
        ],
        "responses": {
          "200": {
            "description": "OK"
          }
        }
      }
    },
    "/api/admin/reports/top-customers": {
      "get": {
        "tags": [
          "Reports"
        ],
        "parameters": [
          {
            "name": "startDate",
            "in": "query",
            "schema": {
              "type": "string",
              "format": "date-time"
            }
          },
          {
            "name": "endDate",
            "in": "query",
            "schema": {
              "type": "string",
              "format": "date-time"
            }
          },
          {
            "name": "limit",
            "in": "query",
            "schema": {
              "type": "integer",
              "format": "int32",
              "default": 10
            }
          }
        ],
        "responses": {
          "200": {
            "description": "OK"
          }
        }
      }
    },
    "/api/admin/suppliers": {
      "get": {
        "tags": [
          "Suppliers"
        ],
        "parameters": [
          {
            "name": "Page",
            "in": "query",
            "schema": {
              "type": "integer",
              "format": "int32"
            }
          },
          {
            "name": "PageSize",
            "in": "query",
            "schema": {
              "type": "integer",
              "format": "int32"
            }
          },
          {
            "name": "Search",
            "in": "query",
            "schema": {
              "type": "string"
            }
          },
          {
            "name": "SortBy",
            "in": "query",
            "schema": {
              "type": "string"
            }
          },
          {
            "name": "SortDesc",
            "in": "query",
            "schema": {
              "type": "boolean"
            }
          }
        ],
        "responses": {
          "200": {
            "description": "OK"
          }
        }
      },
      "post": {
        "tags": [
          "Suppliers"
        ],
        "requestBody": {
          "content": {
            "application/json": {
              "schema": {
                "$ref": "#/components/schemas/CreateSupplierRequest"
              }
            },
            "text/json": {
              "schema": {
                "$ref": "#/components/schemas/CreateSupplierRequest"
              }
            },
            "application/*+json": {
              "schema": {
                "$ref": "#/components/schemas/CreateSupplierRequest"
              }
            }
          }
        },
        "responses": {
          "200": {
            "description": "OK"
          }
        }
      }
    },
    "/api/admin/suppliers/{id}": {
      "get": {
        "tags": [
          "Suppliers"
        ],
        "parameters": [
          {
            "name": "id",
            "in": "path",
            "required": true,
            "schema": {
              "type": "integer",
              "format": "int32"
            }
          }
        ],
        "responses": {
          "200": {
            "description": "OK"
          }
        }
      },
      "put": {
        "tags": [
          "Suppliers"
        ],
        "parameters": [
          {
            "name": "id",
            "in": "path",
            "required": true,
            "schema": {
              "type": "integer",
              "format": "int32"
            }
          }
        ],
        "requestBody": {
          "content": {
            "application/json": {
              "schema": {
                "$ref": "#/components/schemas/UpdateSupplierRequest"
              }
            },
            "text/json": {
              "schema": {
                "$ref": "#/components/schemas/UpdateSupplierRequest"
              }
            },
            "application/*+json": {
              "schema": {
                "$ref": "#/components/schemas/UpdateSupplierRequest"
              }
            }
          }
        },
        "responses": {
          "200": {
            "description": "OK"
          }
        }
      },
      "delete": {
        "tags": [
          "Suppliers"
        ],
        "parameters": [
          {
            "name": "id",
            "in": "path",
            "required": true,
            "schema": {
              "type": "integer",
              "format": "int32"
            }
          }
        ],
        "responses": {
          "200": {
            "description": "OK"
          }
        }
      }
    },
    "/api/admin/users": {
      "get": {
        "tags": [
          "Users"
        ],
        "parameters": [
          {
            "name": "Page",
            "in": "query",
            "schema": {
              "type": "integer",
              "format": "int32"
            }
          },
          {
            "name": "PageSize",
            "in": "query",
            "schema": {
              "type": "integer",
              "format": "int32"
            }
          },
          {
            "name": "Search",
            "in": "query",
            "schema": {
              "type": "string"
            }
          },
          {
            "name": "SortBy",
            "in": "query",
            "schema": {
              "type": "string"
            }
          },
          {
            "name": "SortDesc",
            "in": "query",
            "schema": {
              "type": "boolean"
            }
          }
        ],
        "responses": {
          "200": {
            "description": "OK"
          }
        }
      },
      "post": {
        "tags": [
          "Users"
        ],
        "requestBody": {
          "content": {
            "application/json": {
              "schema": {
                "$ref": "#/components/schemas/CreateUserRequest"
              }
            },
            "text/json": {
              "schema": {
                "$ref": "#/components/schemas/CreateUserRequest"
              }
            },
            "application/*+json": {
              "schema": {
                "$ref": "#/components/schemas/CreateUserRequest"
              }
            }
          }
        },
        "responses": {
          "200": {
            "description": "OK"
          }
        }
      }
    },
    "/api/admin/users/{id}": {
      "get": {
        "tags": [
          "Users"
        ],
        "parameters": [
          {
            "name": "id",
            "in": "path",
            "required": true,
            "schema": {
              "type": "integer",
              "format": "int32"
            }
          }
        ],
        "responses": {
          "200": {
            "description": "OK"
          }
        }
      },
      "put": {
        "tags": [
          "Users"
        ],
        "parameters": [
          {
            "name": "id",
            "in": "path",
            "required": true,
            "schema": {
              "type": "integer",
              "format": "int32"
            }
          }
        ],
        "requestBody": {
          "content": {
            "application/json": {
              "schema": {
                "$ref": "#/components/schemas/UpdateUserRequest"
              }
            },
            "text/json": {
              "schema": {
                "$ref": "#/components/schemas/UpdateUserRequest"
              }
            },
            "application/*+json": {
              "schema": {
                "$ref": "#/components/schemas/UpdateUserRequest"
              }
            }
          }
        },
        "responses": {
          "200": {
            "description": "OK"
          }
        }
      },
      "delete": {
        "tags": [
          "Users"
        ],
        "parameters": [
          {
            "name": "id",
            "in": "path",
            "required": true,
            "schema": {
              "type": "integer",
              "format": "int32"
            }
          }
        ],
        "responses": {
          "200": {
            "description": "OK"
          }
        }
      }
    },
    "/WeatherForecast": {
      "get": {
        "tags": [
          "WeatherForecast"
        ],
        "operationId": "GetWeatherForecast",
        "responses": {
          "200": {
            "description": "OK",
            "content": {
              "text/plain": {
                "schema": {
                  "type": "array",
                  "items": {
                    "$ref": "#/components/schemas/WeatherForecast"
                  }
                }
              },
              "application/json": {
                "schema": {
                  "type": "array",
                  "items": {
                    "$ref": "#/components/schemas/WeatherForecast"
                  }
                }
              },
              "text/json": {
                "schema": {
                  "type": "array",
                  "items": {
                    "$ref": "#/components/schemas/WeatherForecast"
                  }
                }
              }
            }
          }
        }
      }
    }
  },
  "components": {
    "schemas": {
      "AddOrderItemRequest": {
        "required": [
          "productId",
          "quantity"
        ],
        "type": "object",
        "properties": {
          "productId": {
            "type": "integer",
            "format": "int32"
          },
          "quantity": {
            "maximum": 2147483647,
            "minimum": 1,
            "type": "integer",
            "format": "int32"
          }
        },
        "additionalProperties": false
      },
      "CreateCategoryRequest": {
        "required": [
          "categoryName"
        ],
        "type": "object",
        "properties": {
          "categoryName": {
            "maxLength": 100,
            "minLength": 1,
            "type": "string"
          }
        },
        "additionalProperties": false
      },
      "CreateCustomerRequest": {
        "required": [
          "name",
          "phone"
        ],
        "type": "object",
        "properties": {
          "name": {
            "maxLength": 100,
            "minLength": 1,
            "type": "string"
          },
          "phone": {
            "maxLength": 20,
            "minLength": 1,
            "type": "string"
          },
          "email": {
            "maxLength": 100,
            "type": "string",
            "format": "email",
            "nullable": true
          },
          "address": {
            "maxLength": 255,
            "type": "string",
            "nullable": true
          }
        },
        "additionalProperties": false
      },
      "CreateOrderRequest": {
        "required": [
          "customerId",
          "orderItems"
        ],
        "type": "object",
        "properties": {
          "customerId": {
            "type": "integer",
            "format": "int32"
          },
          "promoCode": {
            "maxLength": 50,
            "type": "string",
            "nullable": true
          },
          "orderItems": {
            "minItems": 1,
            "type": "array",
            "items": {
              "$ref": "#/components/schemas/OrderItemInput"
            }
          }
        },
        "additionalProperties": false
      },
      "CreateProductRequest": {
        "required": [
          "barcode",
          "categoryId",
          "price",
          "productName",
          "supplierId",
          "unit"
        ],
        "type": "object",
        "properties": {
          "categoryId": {
            "type": "integer",
            "format": "int32"
          },
          "supplierId": {
            "type": "integer",
            "format": "int32"
          },
          "productName": {
            "maxLength": 100,
            "minLength": 1,
            "type": "string"
          },
          "barcode": {
            "maxLength": 50,
            "minLength": 1,
            "type": "string"
          },
          "price": {
            "minimum": 0.01,
            "type": "number",
            "format": "double"
          },
          "unit": {
            "maxLength": 20,
            "minLength": 1,
            "type": "string"
          }
        },
        "additionalProperties": false
      },
      "CreatePromotionRequest": {
        "required": [
          "discountType",
          "discountValue",
          "endDate",
          "promoCode",
          "startDate",
          "status"
        ],
        "type": "object",
        "properties": {
          "promoCode": {
            "maxLength": 50,
            "minLength": 1,
            "type": "string"
          },
          "description": {
            "maxLength": 255,
            "type": "string",
            "nullable": true
          },
          "discountType": {
            "minLength": 1,
            "pattern": "^(percent|fixed)$",
            "type": "string"
          },
          "discountValue": {
            "minimum": 0.01,
            "type": "number",
            "format": "double"
          },
          "startDate": {
            "type": "string",
            "format": "date-time"
          },
          "endDate": {
            "type": "string",
            "format": "date-time"
          },
          "minOrderAmount": {
            "minimum": 0,
            "type": "number",
            "format": "double"
          },
          "usageLimit": {
            "maximum": 2147483647,
            "minimum": 1,
            "type": "integer",
            "format": "int32"
          },
          "status": {
            "minLength": 1,
            "pattern": "^(active|inactive)$",
            "type": "string"
          }
        },
        "additionalProperties": false
      },
      "CreateSupplierRequest": {
        "required": [
          "name",
          "phone"
        ],
        "type": "object",
        "properties": {
          "name": {
            "maxLength": 100,
            "minLength": 1,
            "type": "string"
          },
          "phone": {
            "maxLength": 20,
            "minLength": 1,
            "type": "string"
          },
          "email": {
            "maxLength": 100,
            "type": "string",
            "nullable": true
          },
          "address": {
            "maxLength": 255,
            "type": "string",
            "nullable": true
          }
        },
        "additionalProperties": false
      },
      "CreateUserRequest": {
        "required": [
          "fullName",
          "password",
          "role",
          "username"
        ],
        "type": "object",
        "properties": {
          "username": {
            "maxLength": 50,
            "minLength": 1,
            "type": "string"
          },
          "password": {
            "minLength": 6,
            "type": "string"
          },
          "fullName": {
            "maxLength": 100,
            "minLength": 1,
            "type": "string"
          },
          "role": {
            "maximum": 1,
            "minimum": 0,
            "type": "integer",
            "format": "int32"
          }
        },
        "additionalProperties": false
      },
      "LoginRequest": {
        "type": "object",
        "properties": {
          "username": {
            "type": "string",
            "nullable": true
          },
          "password": {
            "type": "string",
            "nullable": true
          }
        },
        "additionalProperties": false
      },
      "LogoutRequest": {
        "required": [
          "refreshToken"
        ],
        "type": "object",
        "properties": {
          "refreshToken": {
            "minLength": 1,
            "type": "string"
          }
        },
        "additionalProperties": false
      },
      "OrderItemInput": {
        "required": [
          "productId",
          "quantity"
        ],
        "type": "object",
        "properties": {
          "productId": {
            "type": "integer",
            "format": "int32"
          },
          "quantity": {
            "maximum": 2147483647,
            "minimum": 1,
            "type": "integer",
            "format": "int32"
          }
        },
        "additionalProperties": false
      },
      "RefreshTokenRequest": {
        "required": [
          "accessToken",
          "refreshToken"
        ],
        "type": "object",
        "properties": {
          "accessToken": {
            "minLength": 1,
            "type": "string"
          },
          "refreshToken": {
            "minLength": 1,
            "type": "string"
          }
        },
        "additionalProperties": false
      },
      "UpdateCategoryRequest": {
        "required": [
          "categoryName",
          "id"
        ],
        "type": "object",
        "properties": {
          "id": {
            "type": "integer",
            "format": "int32"
          },
          "categoryName": {
            "maxLength": 100,
            "minLength": 1,
            "type": "string"
          }
        },
        "additionalProperties": false
      },
      "UpdateCustomerRequest": {
        "required": [
          "id",
          "name",
          "phone"
        ],
        "type": "object",
        "properties": {
          "id": {
            "type": "integer",
            "format": "int32"
          },
          "name": {
            "maxLength": 100,
            "minLength": 1,
            "type": "string"
          },
          "phone": {
            "maxLength": 20,
            "minLength": 1,
            "type": "string"
          },
          "email": {
            "maxLength": 100,
            "type": "string",
            "format": "email",
            "nullable": true
          },
          "address": {
            "maxLength": 255,
            "type": "string",
            "nullable": true
          }
        },
        "additionalProperties": false
      },
      "UpdateInventoryRequest": {
        "required": [
          "quantityChange",
          "reason"
        ],
        "type": "object",
        "properties": {
          "quantityChange": {
            "type": "integer",
            "format": "int32"
          },
          "reason": {
            "maxLength": 255,
            "minLength": 1,
            "type": "string"
          }
        },
        "additionalProperties": false
      },
      "UpdateOrderItemRequest": {
        "required": [
          "quantity"
        ],
        "type": "object",
        "properties": {
          "quantity": {
            "maximum": 2147483647,
            "minimum": 1,
            "type": "integer",
            "format": "int32"
          }
        },
        "additionalProperties": false
      },
      "UpdateOrderStatusRequest": {
        "required": [
          "status"
        ],
        "type": "object",
        "properties": {
          "status": {
            "minLength": 1,
            "pattern": "^(paid|canceled)$",
            "type": "string"
          }
        },
        "additionalProperties": false
      },
      "UpdateProductRequest": {
        "required": [
          "barcode",
          "categoryId",
          "id",
          "price",
          "productName",
          "supplierId",
          "unit"
        ],
        "type": "object",
        "properties": {
          "id": {
            "type": "integer",
            "format": "int32"
          },
          "categoryId": {
            "type": "integer",
            "format": "int32"
          },
          "supplierId": {
            "type": "integer",
            "format": "int32"
          },
          "productName": {
            "maxLength": 100,
            "minLength": 1,
            "type": "string"
          },
          "barcode": {
            "maxLength": 50,
            "minLength": 1,
            "type": "string"
          },
          "price": {
            "minimum": 0.01,
            "type": "number",
            "format": "double"
          },
          "unit": {
            "maxLength": 20,
            "minLength": 1,
            "type": "string"
          }
        },
        "additionalProperties": false
      },
      "UpdatePromotionRequest": {
        "required": [
          "discountType",
          "discountValue",
          "endDate",
          "id",
          "promoCode",
          "startDate",
          "status"
        ],
        "type": "object",
        "properties": {
          "id": {
            "type": "integer",
            "format": "int32"
          },
          "promoCode": {
            "maxLength": 50,
            "minLength": 1,
            "type": "string"
          },
          "description": {
            "maxLength": 255,
            "type": "string",
            "nullable": true
          },
          "discountType": {
            "minLength": 1,
            "pattern": "^(percent|fixed)$",
            "type": "string"
          },
          "discountValue": {
            "minimum": 0.01,
            "type": "number",
            "format": "double"
          },
          "startDate": {
            "type": "string",
            "format": "date-time"
          },
          "endDate": {
            "type": "string",
            "format": "date-time"
          },
          "minOrderAmount": {
            "minimum": 0,
            "type": "number",
            "format": "double"
          },
          "usageLimit": {
            "maximum": 2147483647,
            "minimum": 1,
            "type": "integer",
            "format": "int32"
          },
          "status": {
            "minLength": 1,
            "pattern": "^(active|inactive)$",
            "type": "string"
          }
        },
        "additionalProperties": false
      },
      "UpdateSupplierRequest": {
        "required": [
          "id",
          "name",
          "phone"
        ],
        "type": "object",
        "properties": {
          "id": {
            "type": "integer",
            "format": "int32"
          },
          "name": {
            "maxLength": 100,
            "minLength": 1,
            "type": "string"
          },
          "phone": {
            "maxLength": 20,
            "minLength": 1,
            "type": "string"
          },
          "email": {
            "maxLength": 100,
            "type": "string",
            "nullable": true
          },
          "address": {
            "maxLength": 255,
            "type": "string",
            "nullable": true
          }
        },
        "additionalProperties": false
      },
      "UpdateUserRequest": {
        "required": [
          "fullName",
          "id",
          "role",
          "username"
        ],
        "type": "object",
        "properties": {
          "id": {
            "type": "integer",
            "format": "int32"
          },
          "username": {
            "maxLength": 50,
            "minLength": 1,
            "type": "string"
          },
          "password": {
            "maxLength": 255,
            "type": "string",
            "nullable": true
          },
          "fullName": {
            "maxLength": 100,
            "minLength": 1,
            "type": "string"
          },
          "role": {
            "maximum": 1,
            "minimum": 0,
            "type": "integer",
            "format": "int32"
          }
        },
        "additionalProperties": false
      },
      "ValidatePromoRequest": {
        "required": [
          "orderAmount",
          "promoCode"
        ],
        "type": "object",
        "properties": {
          "promoCode": {
            "minLength": 1,
            "type": "string"
          },
          "orderAmount": {
            "minimum": 0.01,
            "type": "number",
            "format": "double"
          }
        },
        "additionalProperties": false
      },
      "WeatherForecast": {
        "type": "object",
        "properties": {
          "date": {
            "type": "string",
            "format": "date"
          },
          "temperatureC": {
            "type": "integer",
            "format": "int32"
          },
          "temperatureF": {
            "type": "integer",
            "format": "int32",
            "readOnly": true
          },
          "summary": {
            "type": "string",
            "nullable": true
          }
        },
        "additionalProperties": false
      }
    },
    "securitySchemes": {
      "Bearer": {
        "type": "http",
        "description": "Please enter a valid token",
        "scheme": "Bearer",
        "bearerFormat": "JWT"
      }
    }
  },
  "security": [
    {
      "Bearer": [ ]
    }
  ]
}